berroutils/__init__.py
berroutils/crypter.py
berroutils/utils.py
berroutils/container/__init__.py
berroutils/container/list_of_dict_container.py
berroutils/plugins/__init__.py
berroutils/plugins/file_handler.py
berroutils-0.2.0.dist-info/METADATA
berroutils-0.2.0.dist-info/WHEEL
berroutils-0.2.0.dist-info/licenses/LICENSE
berroutils-0.2.0.dist-info/RECORD
