Metadata-Version: 2.4
Name: berroutils
Version: 0.2.0
Summary: Python utilities
Project-URL: Homepage, https://github.com/berroniko/berroutils
Project-URL: Issues, https://github.com/berroniko/berroutils/issues
Author-email: Berroniko <buzones-git@yahoo.com>
License-Expression: MPL-2.0
License-File: LICENSE
Classifier: Operating System :: OS Independent
Classifier: Programming Language :: Python :: 3
Requires-Python: >=3.10
Requires-Dist: cryptography>=44.0.3
Requires-Dist: pandas>=2.2.3
Requires-Dist: pytest>=8.3.5
